odoo9_addon_purchase_operating_unit-9.0.1.0.0.99.dev6-py2.7-nspkg.pth
odoo9_addon_purchase_operating_unit-9.0.1.0.0.99.dev6.dist-info/DESCRIPTION.rst
odoo9_addon_purchase_operating_unit-9.0.1.0.0.99.dev6.dist-info/METADATA
odoo9_addon_purchase_operating_unit-9.0.1.0.0.99.dev6.dist-info/RECORD
odoo9_addon_purchase_operating_unit-9.0.1.0.0.99.dev6.dist-info/WHEEL
odoo9_addon_purchase_operating_unit-9.0.1.0.0.99.dev6.dist-info/metadata.json
odoo9_addon_purchase_operating_unit-9.0.1.0.0.99.dev6.dist-info/namespace_packages.txt
odoo9_addon_purchase_operating_unit-9.0.1.0.0.99.dev6.dist-info/top_level.txt
odoo_addons/purchase_operating_unit/README.rst
odoo_addons/purchase_operating_unit/__init__.py
odoo_addons/purchase_operating_unit/__openerp__.py
odoo_addons/purchase_operating_unit/demo/purchase_order_demo.xml
odoo_addons/purchase_operating_unit/models/__init__.py
odoo_addons/purchase_operating_unit/models/invoice.py
odoo_addons/purchase_operating_unit/models/procurement.py
odoo_addons/purchase_operating_unit/models/purchase.py
odoo_addons/purchase_operating_unit/security/purchase_security.xml
odoo_addons/purchase_operating_unit/static/description/icon.png
odoo_addons/purchase_operating_unit/tests/__init__.py
odoo_addons/purchase_operating_unit/tests/test_po_security.py
odoo_addons/purchase_operating_unit/tests/test_purchase_operating_unit.py
odoo_addons/purchase_operating_unit/views/purchase_order_line_view.xml
odoo_addons/purchase_operating_unit/views/purchase_order_view.xml
